gitload/bitbucket/__init__.py
gitload/bitbucket/_bitbucket.py
gitload/github/__init__.py
gitload/github/_github.py
gitload-1.0.dist-info/AUTHORS
gitload-1.0.dist-info/LICENSE
gitload-1.0.dist-info/METADATA
gitload-1.0.dist-info/WHEEL
gitload-1.0.dist-info/top_level.txt
gitload-1.0.dist-info/RECORD
