Metadata-Version: 2.1
Name: gitload
Version: 1.0
Summary: Python API for downloading web-repositories
Home-page: https://github.com/syubogdanov/gitload
Author: Sergei Bogdanov
Author-email: syubogdanov@outlook.com
License: MIT
Classifier: License :: OSI Approved :: MIT License
Classifier: Operating System :: OS Independent
Classifier: Programming Language :: Python :: 3.7
Classifier: Programming Language :: Python :: 3.8
Classifier: Programming Language :: Python :: 3.9
Classifier: Programming Language :: Python :: 3.10
Classifier: Programming Language :: Python :: 3.11
Classifier: Programming Language :: Python :: 3.12
License-File: LICENSE
License-File: AUTHORS
